Workbook
Name aporte: Simulador!$D$17
Name patrimonio: Simulador!$D$20
Name qtd_anos: Simulador!$D$18
Name Rendimento_carteira: Simulador!$D$13
Name salario: Simulador!$D$12
Name sugestao_investimento: Simulador!$D$14
Name taxa_mensal: Simulador!$D$19

Sheet Simulador
B11: CONFIGURAÇÕES
B12: Salário | D12: 5000
B13: Redimentos Carteira | D13: 0.006
B14: Sugestão de Investimentos | D14: =D12*30% -> 1500
B16: INVESTIMENTO MENSAL
B17: Quanto investir por mês? | D17: 500
B18: Por quantos anos? | D18: 5
B19: Taxa de rendimento mensal? | D19: 0.01079
B20: Patrimônio acumulado? | D20: =FV(taxa_mensal,qtd_anos*12,aporte*-1) -> 41888.457
B21: Dividendos Mensais? | D21: =patrimonio*Rendimento_carteira -> 251.33074
B23: CENÁRIOS | D23: Dividendos
A24: 2 | B24: Quantos em 2 anos? | C24: =FV($D$19,A$24*12,$D$17*-1) -> 13613.814 | D24: =C24*Rendimento_carteira -> 81.682882
A25: 5 | B25: Quanto em 5 anos? | C25: =FV($D$19,A$25*12,$D$17*-1) -> 41888.457 | D25: =C25*Rendimento_carteira -> 251.33074
A26: 10 | B26: Quanto em 10 anos? | C26: =FV($D$19,A$26*12,$D$17*-1) -> 121642.11 | D26: =C26*Rendimento_carteira -> 729.85264
A27: 20 | B27: Quanto em 20 anos? | C27: =FV($D$19,A$27*12,$D$17*-1) -> 562599.2 | D27: =C27*Rendimento_carteira -> 3375.5952
A28: 30 | B28: Quanto em 30 anos? | C28: =FV($D$19,A28*12,$D$17*-1) -> 2161084.8 | D28: =C28*Rendimento_carteira -> 12966.509
B31: PERFIL | C31: Moderado
B32: VALOR A SER INVESTIDO POR MÊS | C32: =aporte -> 500
B34: TIPO DE FII | C34: PORCENTUAL SUGERIDO | D34: VALORES
B35: PAPEL | C35: =VLOOKUP($C$31&"."&B35,Data!$A:$D,4,) -> 0.32 | D35: =C35*$C$32 -> 160
B36: TIJOLO | C36: =VLOOKUP($C$31&"."&B36,Data!$A:$D,4,) -> 0.35 | D36: =C36*$C$32 -> 175
B37: HÍBRIDOS | C37: =VLOOKUP($C$31&"."&B37,Data!$A:$D,4,) -> 0.08 | D37: =C37*$C$32 -> 40
B38: FOFs | C38: =VLOOKUP($C$31&"."&B38,Data!$A:$D,4,) -> 0.05 | D38: =C38*$C$32 -> 25
B39: DESENVOLVIMENTO | C39: =VLOOKUP($C$31&"."&B39,Data!$A:$D,4,) -> 0.1 | D39: =C39*$C$32 -> 50
B40: HOTELARIAS | C40: =VLOOKUP($C$31&"."&B40,Data!$A:$D,4,) -> 0.1 | D40: =C40*$C$32 -> 50
D41: =SUM(D35:D40) -> 500

Sheet Data
A2: Chave | B2: Perfil | C2: Tipo de FII | D2: %
A3: =B3&"."&C3 -> Conservador.PAPEL | B3: Conservador | C3: PAPEL | D3: 0.3
A4: =B4&"."&C4 -> Conservador.TIJOLO | B4: Conservador | C4: TIJOLO | D4: 0.5
A5: =B5&"."&C5 -> Conservador.HÍBRIDOS | B5: Conservador | C5: HÍBRIDOS | D5: 0.1 | H5: %
A6: =B6&"."&C6 -> Conservador.FOFs | B6: Conservador | C6: FOFs | D6: 0.1 | G6: Moderado.TIJOLO | H6: =VLOOKUP(G6,$A:$D,4,FALSE) -> 0.35
A7: =B7&"."&C7 -> Conservador.DESENVOLVIMENTO | B7: Conservador | C7: DESENVOLVIMENTO | D7: 0
A8: =B8&"."&C8 -> Conservador.HOTELARIAS | B8: Conservador | C8: HOTELARIAS | D8: 0
A9: =B9&"."&C9 -> Moderado.PAPEL | B9: Moderado | C9: PAPEL | D9: 0.32
A10: =B10&"."&C10 -> Moderado.TIJOLO | B10: Moderado | C10: TIJOLO | D10: 0.35
A11: =B11&"."&C11 -> Moderado.HÍBRIDOS | B11: Moderado | C11: HÍBRIDOS | D11: 0.08
A12: =B12&"."&C12 -> Moderado.FOFs | B12: Moderado | C12: FOFs | D12: 0.05
A13: =B13&"."&C13 -> Moderado.DESENVOLVIMENTO | B13: Moderado | C13: DESENVOLVIMENTO | D13: 0.1
A14: =B14&"."&C14 -> Moderado.HOTELARIAS | B14: Moderado | C14: HOTELARIAS | D14: 0.1
A15: =B15&"."&C15 -> Agressivo.PAPEL | B15: Agressivo | C15: PAPEL | D15: 0.5
A16: =B16&"."&C16 -> Agressivo.TIJOLO | B16: Agressivo | C16: TIJOLO | D16: 0.1
A17: =B17&"."&C17 -> Agressivo.HÍBRIDOS | B17: Agressivo | C17: HÍBRIDOS | D17: 0.05
A18: =B18&"."&C18 -> Agressivo.FOFs | B18: Agressivo | C18: FOFs | D18: 0.05
... A20: =B20&"."&C20 -> Agressivo.HOTELARIAS | B20: Agressivo | C20: HOTELARIAS | D20: 0.1
